refdatatypes/VERSION
refdatatypes/__init__.py
refdatatypes/refbase.py
refdatatypes/refbool.py
refdatatypes/reffloat.py
refdatatypes/refint.py
refdatatypes/refstr.py
refdatatypes/safedatatypes.py
refdatatypes/test_class_static.py
refdatatypes/test_refbool.py
refdatatypes/test_reffloat.py
refdatatypes/test_refint.py
refdatatypes/test_safedatatypes.py
refdatatypes/test_utils.py
refdatatypes/utils.py
refdatatypes-1.4.1.dist-info/METADATA
refdatatypes-1.4.1.dist-info/WHEEL
refdatatypes-1.4.1.dist-info/top_level.txt
refdatatypes-1.4.1.dist-info/RECORD
