Metadata-Version: 2.1
Name: refdatatypes
Version: 1.4.1
Summary: Pyton basic datatypes as a references.
Home-page: https://gitlab.com/alda78/refdatatypes
Author: Ales Adamek
Author-email: alda78@seznam.cz
License: MIT
Classifier: Programming Language :: Python :: 3
Classifier: License :: OSI Approved :: MIT License
Classifier: Operating System :: OS Independent
Requires-Python: >=3.7
